halcon/__init__.py
halcon/errors.py
halcon/ffi.py
halcon/hdev_operator.py
halcon/hdevengine.py
halcon/hhandle.py
halcon/hobject.py
halcon/interop.py
halcon/meta.py
halcon/mixin.py
halcon/numpy_interop.py
halcon/operator_set.py
halcon/python_interop.py
halcon/util.py
mvtec_halcon-25050.0.0.dist-info/METADATA
mvtec_halcon-25050.0.0.dist-info/WHEEL
mvtec_halcon-25050.0.0.dist-info/licenses/eula.html
mvtec_halcon-25050.0.0.dist-info/RECORD
