Metadata-Version: 2.1
Name: mvtec-halcon
Version: 25050.0.0
Summary: Native Python language bindings for MVTec HALCON.
Project-URL: Product Page, https://www.mvtec.com/products/halcon
Project-URL: Documentation, https://www.mvtec.com/products/halcon/work-with-halcon/documentation
Author-email: MVTec Software GmbH <info@mvtec.com>
License-File: eula.html
Keywords: HALCON,MVTec,image,processing
Classifier: Development Status :: 5 - Production/Stable
Classifier: Intended Audience :: Developers
Classifier: License :: Other/Proprietary License
Classifier: Natural Language :: English
Classifier: Programming Language :: Python :: 3.8
Classifier: Programming Language :: Python :: Implementation :: CPython
Classifier: Topic :: Scientific/Engineering :: Image Processing
Classifier: Topic :: Scientific/Engineering :: Visualization
Requires-Python: >=3.8
